orchagent/__init__.py
orchagent/client.py
orchagent/py.typed
orchagent_sdk-0.1.0.dist-info/METADATA
orchagent_sdk-0.1.0.dist-info/WHEEL
orchagent_sdk-0.1.0.dist-info/top_level.txt
orchagent_sdk-0.1.0.dist-info/RECORD
