Metadata-Version: 2.4
Name: orchagent-sdk
Version: 0.1.0
Summary: SDK for building OrchAgent agents - enables agent-to-agent calls with local execution support
License: MIT
Project-URL: Homepage, https://orchagent.io
Project-URL: Documentation, https://docs.orchagent.io
Project-URL: Repository, https://github.com/jp730/orchagent-sdk
Keywords: orchagent,agents,ai,sdk
Classifier: Development Status :: 4 - Beta
Classifier: Intended Audience :: Developers
Classifier: License :: OSI Approved :: MIT License
Classifier: Programming Language :: Python :: 3
Classifier: Programming Language :: Python :: 3.10
Classifier: Programming Language :: Python :: 3.11
Classifier: Programming Language :: Python :: 3.12
Classifier: Topic :: Software Development :: Libraries :: Python Modules
Requires-Python: >=3.10
Requires-Dist: httpx>=0.26.0
Provides-Extra: dev
Requires-Dist: pytest>=8.0.0; extra == "dev"
Requires-Dist: pytest-asyncio>=0.23.0; extra == "dev"
